LICENSE
MANIFEST.in
README.md
setup.py
icons/__init__.py
icons/gui.py
icons.egg-info/PKG-INFO
icons.egg-info/SOURCES.txt
icons.egg-info/dependency_links.txt
icons.egg-info/entry_points.txt
icons.egg-info/requires.txt
icons.egg-info/top_level.txt
icons/tkdnd/darwin/libtkdnd2.7.dylib
icons/tkdnd/darwin/pkgIndex.tcl
icons/tkdnd/darwin/tkdnd.tcl
icons/tkdnd/darwin/tkdnd_compat.tcl
icons/tkdnd/darwin/tkdnd_generic.tcl
icons/tkdnd/darwin/tkdnd_macosx.tcl
icons/tkdnd/darwin/tkdnd_unix.tcl
icons/tkdnd/darwin/tkdnd_windows.tcl
icons/tkdnd/win32/libtkdnd2.7.dll
icons/tkdnd/win32/pkgIndex.tcl
icons/tkdnd/win32/tkdnd.tcl
icons/tkdnd/win32/tkdnd_compat.tcl
icons/tkdnd/win32/tkdnd_generic.tcl
icons/tkdnd/win32/tkdnd_macosx.tcl
icons/tkdnd/win32/tkdnd_unix.tcl
icons/tkdnd/win32/tkdnd_windows.tcl