Metadata-Version: 1.0
Name: icons
Version: 1.1
Summary: generate icons of all sizes and config file (e.g. Contents.json) required by iOS or Android app, inspired by http://makeappicon.com
Home-page: http://github.com/exherb/icons
Author: Herb Brewer
Author-email: i@4leaf.me
License: MIT
Keywords: icon ios android
Platform: UNKNOWN
